package fr.unedic.cali.calcul.dom.periode.pc;

import fr.unedic.transverse.dom.spec.DomPCSpec;
import fr.unedic.util.temps.ObjetChronoPeriodePC;
import fr.unedic.util.temps.Periode;
import java.io.IOException;
import java.io.ObjectOutputStream;
import javax.jdo.JDOFatalInternalException;
import javax.jdo.JDOUnsupportedOptionException;
import javax.jdo.JDOUserException;
import javax.jdo.PersistenceManager;
import javax.jdo.spi.JDOImplHelper;
import javax.jdo.spi.JDOPermission;
import javax.jdo.spi.PersistenceCapable;
import javax.jdo.spi.PersistenceCapable.ObjectIdFieldConsumer;
import javax.jdo.spi.PersistenceCapable.ObjectIdFieldSupplier;
import javax.jdo.spi.StateManager;
import xcalia.lido.internal.sm.CommonStateManager;

public abstract class PeriodeNonDeclareeSanctionPC
  extends ObjetChronoPeriodePC
  implements DomPCSpec, PersistenceCapable
{
  protected transient byte jdoFlags;
  protected transient StateManager jdoStateManager;
  private static int jdoInheritedFieldCount = 0;
  private static String[] jdoFieldNames = { "m_periode" };
  private static Class[] jdoFieldTypes = { Periode.class };
  private static byte[] jdoFieldFlags = { (byte)(PersistenceCapable.CHECK_READ + PersistenceCapable.CHECK_WRITE) };
  private static Class jdoPersistenceCapableSuperclass = null;
  static final long serialVersionUID = -8556049292349008132L;
  
  public abstract Object createOM();
  
  static
  {
    JDOImplHelper.registerClass(PeriodeNonDeclareeSanctionPC.class, jdoFieldNames, jdoFieldTypes, jdoFieldFlags, jdoPersistenceCapableSuperclass, null);
  }
  
  protected static final Periode jdoGetm_periode(PeriodeNonDeclareeSanctionPC pc)
  {
    if (jdoFlags <= 0) {
      return m_periode;
    }
    StateManager sm = jdoStateManager;
    if (sm != null)
    {
      if (sm.isLoaded(pc, jdoInheritedFieldCount + 0)) {
        return m_periode;
      }
      return (Periode)sm.getObjectField(pc, jdoInheritedFieldCount + 0, m_periode);
    }
    return m_periode;
  }
  
  protected static final void jdoSetm_periode(PeriodeNonDeclareeSanctionPC pc, Periode newValue)
  {
    if (jdoFlags == 0)
    {
      m_periode = newValue;
      return;
    }
    StateManager sm = jdoStateManager;
    if (sm != null) {
      sm.setObjectField(pc, jdoInheritedFieldCount + 0, m_periode, newValue);
    } else {
      m_periode = newValue;
    }
  }
  
  public void jdoProvideField(int fieldNumber)
  {
    int relativeField = fieldNumber - jdoInheritedFieldCount;
    switch (relativeField)
    {
    case 0: 
      jdoStateManager.providedObjectField(this, fieldNumber, m_periode);
      break;
    default: 
      throw new JDOFatalInternalException("index of field is out of bound");
    }
  }
  
  public void jdoReplaceField(int fieldNumber)
  {
    int relativeField = fieldNumber - jdoInheritedFieldCount;
    switch (relativeField)
    {
    case 0: 
      m_periode = ((Periode)jdoStateManager.replacingObjectField(this, fieldNumber));
      break;
    default: 
      throw new JDOFatalInternalException("index of field is out of bound");
    }
  }
  
  public void jdoProvideFields(int[] fieldNumbers)
  {
    for (int i = 0; i < fieldNumbers.length; i++)
    {
      int fieldNumber = fieldNumbers[i];
      jdoProvideField(fieldNumber);
    }
  }
  
  public void jdoReplaceFields(int[] fieldNumbers)
  {
    for (int i = 0; i < fieldNumbers.length; i++)
    {
      int fieldNumber = fieldNumbers[i];
      jdoReplaceField(fieldNumber);
    }
  }
  
  public synchronized void jdoReplaceStateManager(StateManager sm)
  {
    if (jdoStateManager != null)
    {
      jdoStateManager = jdoStateManager.replacingStateManager(this, sm);
    }
    else
    {
      SecurityManager securityManager = System.getSecurityManager();
      if (securityManager != null) {
        securityManager.checkPermission(JDOPermission.SET_STATE_MANAGER);
      }
      jdoStateManager = sm;
    }
  }
  
  public boolean jdoIsPersistent()
  {
    if (jdoStateManager != null) {
      return jdoStateManager.isPersistent(this);
    }
    return false;
  }
  
  public boolean jdoIsTransactional()
  {
    if (jdoStateManager != null) {
      return jdoStateManager.isTransactional(this);
    }
    return false;
  }
  
  public boolean jdoIsNew()
  {
    if (jdoStateManager != null) {
      return jdoStateManager.isNew(this);
    }
    return false;
  }
  
  public boolean jdoIsDirty()
  {
    if (jdoStateManager != null) {
      return jdoStateManager.isDirty(this);
    }
    return false;
  }
  
  public boolean jdoIsDeleted()
  {
    if (jdoStateManager != null) {
      return jdoStateManager.isDeleted(this);
    }
    return false;
  }
  
  public void jdoMakeDirty(String fieldName)
  {
    if (jdoStateManager != null) {
      jdoStateManager.makeDirty(this, fieldName);
    }
  }
  
  public void jdoReplaceFlags()
  {
    if (jdoStateManager != null)
    {
      jdoFlags = jdoStateManager.replacingFlags(this);
      return;
      jdoFlags = 0;
    }
  }
  
  public boolean jdoIsDetached()
  {
    if (jdoStateManager != null) {
      return ((CommonStateManager)jdoStateManager).isDetached();
    }
    return false;
  }
  
  /* Error */
  public PersistenceCapable jdoNewInstance(StateManager sm)
  {
    // Byte code:
    //   0: new 23	javax/jdo/JDOFatalInternalException
    //   3: dup
    //   4: ldc -26
    //   6: invokespecial 144	javax/jdo/JDOFatalInternalException:<init>	(Ljava/lang/String;)V
    //   9: athrow
    //   10: areturn
    // Local variable table:
    //   start	length	slot	name	signature
    //   0	11	0	this	PeriodeNonDeclareeSanctionPC
    //   0	11	1	sm	StateManager
  }
  
  /* Error */
  public PersistenceCapable jdoNewInstance(StateManager sm, Object oid)
  {
    // Byte code:
    //   0: new 23	javax/jdo/JDOFatalInternalException
    //   3: dup
    //   4: ldc -26
    //   6: invokespecial 144	javax/jdo/JDOFatalInternalException:<init>	(Ljava/lang/String;)V
    //   9: athrow
    //   10: areturn
    // Local variable table:
    //   start	length	slot	name	signature
    //   0	11	0	this	PeriodeNonDeclareeSanctionPC
    //   0	11	1	sm	StateManager
    //   0	11	2	oid	Object
  }
  
  public static int jdoGetManagedFieldCount()
  {
    return jdoInheritedFieldCount + 1;
  }
  
  public void jdoCopyFields(Object pc, int[] fieldNumbers)
  {
    if (!(pc instanceof PeriodeNonDeclareeSanctionPC)) {
      throw new JDOFatalInternalException("Can't copy fields from a different class");
    }
    PeriodeNonDeclareeSanctionPC other = (PeriodeNonDeclareeSanctionPC)pc;
    if (jdoStateManager != jdoStateManager) {
      throw new JDOUserException("Source object should have the same StateManager");
    }
    for (int i = 0; i < fieldNumbers.length; i++)
    {
      int relativeField = fieldNumbers[i] - jdoInheritedFieldCount;
      switch (relativeField)
      {
      case 0: 
        m_periode = m_periode;
      }
    }
  }
  
  public void jdoCopyKeyFieldsToObjectId(Object object)
  {
    throw new JDOUnsupportedOptionException("Can't be used without Application Identity");
  }
  
  public void jdoCopyKeyFieldsToObjectId(PersistenceCapable.ObjectIdFieldSupplier supplier, Object object)
  {
    throw new JDOUnsupportedOptionException("Can't be used without Application Identity");
  }
  
  protected void jdoCopyKeyFieldsFromObjectId(Object object) {}
  
  public void jdoCopyKeyFieldsFromObjectId(PersistenceCapable.ObjectIdFieldConsumer consumer, Object object)
  {
    throw new JDOUnsupportedOptionException("Can't be used without Application Identity");
  }
  
  public Object jdoNewObjectIdInstance()
  {
    return null;
  }
  
  public Object jdoNewObjectIdInstance(Object str)
  {
    return null;
  }
  
  public Object jdoGetObjectId()
  {
    if (jdoStateManager != null) {
      return jdoStateManager.getObjectId(this);
    }
    return null;
  }
  
  public PersistenceManager jdoGetPersistenceManager()
  {
    if (jdoStateManager != null) {
      return jdoStateManager.getPersistenceManager(this);
    }
    return null;
  }
  
  private void jdoPreSerialize()
  {
    if (jdoStateManager != null) {
      jdoStateManager.preSerialize(this);
    }
  }
  
  private void writeObject(ObjectOutputStream out)
    throws IOException
  {
    jdoPreSerialize();
    out.defaultWriteObject();
  }
  
  public Object jdoGetTransactionalObjectId()
  {
    if (jdoStateManager != null) {
      return jdoStateManager.getTransactionalObjectId(this);
    }
    return null;
  }
}

/* Location:
 * Qualified Name:     PeriodeNonDeclareeSanctionPC
 * Java Class Version: 6 (50.0)
 * JD-Core Version:    0.7.1
 */